PreDoCS/__init__.py
PreDoCS/_version.py
PreDoCS/CrossSectionAnalysis/CrossSectionGeometry.py
PreDoCS/CrossSectionAnalysis/DiscreetCrossSectionGeometry.py
PreDoCS/CrossSectionAnalysis/Display.py
PreDoCS/CrossSectionAnalysis/Export.py
PreDoCS/CrossSectionAnalysis/Interfaces.py
PreDoCS/CrossSectionAnalysis/Processors.py
PreDoCS/CrossSectionAnalysis/__init__.py
PreDoCS/LoadAnalysis/Interfaces.py
PreDoCS/LoadAnalysis/Load.py
PreDoCS/LoadAnalysis/__init__.py
PreDoCS/LoadAnalysis/load_processor.py
PreDoCS/MaterialAnalysis/CLT.py
PreDoCS/MaterialAnalysis/ElementProperties.py
PreDoCS/MaterialAnalysis/Interfaces.py
PreDoCS/MaterialAnalysis/Materials.py
PreDoCS/MaterialAnalysis/Shells.py
PreDoCS/MaterialAnalysis/__init__.py
PreDoCS/ResultsViewer/__init__.py
PreDoCS/ResultsViewer/run.py
PreDoCS/ResultsViewer/views.py
PreDoCS/ResultsViewer/ui/MainWindow.py
PreDoCS/ResultsViewer/ui/MainWindow_ui.py
PreDoCS/ResultsViewer/ui/__init__.py
PreDoCS/SolverInterface/SolverInterfaceBase.py
PreDoCS/SolverInterface/SolverInterfaceLightworks.py
PreDoCS/SolverInterface/SolverInterfacePreDoCS.py
PreDoCS/SolverInterface/__init__.py
PreDoCS/WingAnalysis/BeamFEM.py
PreDoCS/WingAnalysis/CPACS2PreDoCS.py
PreDoCS/WingAnalysis/Display.py
PreDoCS/WingAnalysis/PreDoCSCoord.py
PreDoCS/WingAnalysis/__init__.py
PreDoCS/WingAnalysis/cpacs_interface_predocs.py
PreDoCS/notebook_utils/__init__.py
PreDoCS/notebook_utils/comparison.py
PreDoCS/notebook_utils/sympy.py
PreDoCS/util/Logging.py
PreDoCS/util/MinimalCycleBasis.py
PreDoCS/util/__init__.py
PreDoCS/util/data.py
PreDoCS/util/dtypes.py
PreDoCS/util/filters.py
PreDoCS/util/geometry.py
PreDoCS/util/globals.py
PreDoCS/util/inout.py
PreDoCS/util/occ.py
PreDoCS/util/util.py
PreDoCS/util/vector.py
shellexpander/__init__.py
shellexpander/shellexpander.py
test/Comparison.py
test/CrossSections.py
test/Testing.py
test/__init__.py
test/tests/__init__.py
test/tests/conftest.py
test/tests/CrossSectionAnalysis/__init__.py
predocs-1.3.0.dist-info/LICENSE.md
predocs-1.3.0.dist-info/METADATA
predocs-1.3.0.dist-info/WHEEL
predocs-1.3.0.dist-info/entry_points.txt
predocs-1.3.0.dist-info/top_level.txt
predocs-1.3.0.dist-info/RECORD
