Metadata-Version: 2.1
Name: predocs
Version: 1.3.0
Summary: PreDoCS (Preliminary Design of Composite Structures) is Python tool for a fast evaluation of wing structure concepts i.e. for a multi-disciplinary design optimization.
Author-email: Edgar Werthen <edgar.werthen@dlr.de>, Daniel Hardt <daniel@daniel-hardt.de>
License: <!--
Project-URL: Homepage, https://gitlab.dlr.de/vcp/predocs/predocs/
Project-URL: Documentation, https://vcp.pages.gitlab.dlr.de/predocs/predocs/
Project-URL: Homepage standalone, https://gitlab.com/DLR-SY/predocs
Project-URL: Documentation standalone, https://dlr-sy.gitlab.io/predocs
Requires-Python: >=3.11
License-File: LICENSE.md
Requires-Dist: numpy<2
Requires-Dist: scipy
Requires-Dist: pandas
Requires-Dist: matplotlib
Requires-Dist: networkx
Requires-Dist: cloudpickle
Requires-Dist: deepdiff
Requires-Dist: openpyxl
Requires-Dist: cython
Requires-Dist: ruamel.yaml
Provides-Extra: full
Requires-Dist: openpyxl; extra == "full"
Requires-Dist: PySide6; extra == "full"
Requires-Dist: pillow; extra == "full"
Requires-Dist: sympy; extra == "full"
Requires-Dist: jupyter; extra == "full"
Requires-Dist: mathjax; extra == "full"
Provides-Extra: build-docs
Requires-Dist: sphinx; extra == "build-docs"
Requires-Dist: sphinx_rtd_theme; extra == "build-docs"
Requires-Dist: myst_parser; extra == "build-docs"
Requires-Dist: pandoc; extra == "build-docs"
Requires-Dist: jupyter; extra == "build-docs"
Requires-Dist: sympy; extra == "build-docs"
Requires-Dist: pillow; extra == "build-docs"
Requires-Dist: nbsphinx; extra == "build-docs"
Requires-Dist: h5py; extra == "build-docs"
Provides-Extra: tests
Requires-Dist: pytest; extra == "tests"
Requires-Dist: pytest-env; extra == "tests"
Requires-Dist: pytest-cov; extra == "tests"
Requires-Dist: pytest-xdist; extra == "tests"
Requires-Dist: pytest-durations; extra == "tests"
Requires-Dist: coverage; extra == "tests"
Requires-Dist: nbval; extra == "tests"
Requires-Dist: h5py; extra == "tests"
Requires-Dist: deepdiff; extra == "tests"
